django_resckeditor-1.0.0.dist-info/METADATA
django_resckeditor-1.0.0.dist-info/RECORD
django_resckeditor-1.0.0.dist-info/WHEEL
django_resckeditor-1.0.0.dist-info/top_level.txt
resckeditor/__init__.py
resckeditor/admin.py
resckeditor/apps.py
resckeditor/models.py
resckeditor/tests.py
resckeditor/urls.py
resckeditor/views.py
resckeditor/locale/it/LC_MESSAGES/django.mo
resckeditor/locale/it/LC_MESSAGES/django.po
resckeditor/locale/it/LC_MESSAGES/djangojs.mo
resckeditor/locale/it/LC_MESSAGES/djangojs.po
resckeditor/static/ckeditor/ckeditor/plugins/resource/plugin.js
resckeditor/static/ckeditor/ckeditor/plugins/resource/dialogs/resource.js
resckeditor/static/ckeditor/ckeditor/plugins/resource/icons/res.png
