Metadata-Version: 2.1
Name: django-resckeditor
Version: 1.0.0
Summary: A django app which provides and infrastructure you can use to include custom contents of other apps directly inside ckeditor.
Home-page: http://github.com/otto-torino/django-resckeditor
Author: abidibo
Author-email: abidibo@gmail.com
License: MIT License
Platform: UNKNOWN
Classifier: Environment :: Web Environment
Classifier: Framework :: Django
Classifier: Intended Audience :: Developers
Classifier: Intended Audience :: System Administrators
Classifier: License :: OSI Approved :: MIT License
Classifier: Operating System :: OS Independent
Classifier: Programming Language :: Python
Classifier: Programming Language :: Python :: 2.5
Classifier: Programming Language :: Python :: 2.6
Classifier: Programming Language :: Python :: 2.7
Classifier: Programming Language :: Python :: 3.2
Classifier: Programming Language :: Python :: 3.3
Classifier: Programming Language :: Python :: 3.5
Classifier: Topic :: Software Development
Classifier: Topic :: Internet :: WWW/HTTP :: Dynamic Content
Requires-Dist: django-ckeditor
